dgl/__init__.py
dgl/_api_internal.py
dgl/base.py
dgl/batch.py
dgl/container.py
dgl/convert.py
dgl/core.py
dgl/frame.py
dgl/generators.py
dgl/graph_index.py
dgl/heterograph.py
dgl/heterograph_index.py
dgl/init.py
dgl/libdgl.so
dgl/ndarray.py
dgl/network.py
dgl/partition.py
dgl/propagate.py
dgl/random.py
dgl/readout.py
dgl/sparse.py
dgl/subgraph.py
dgl/transform.py
dgl/traversal.py
dgl/udf.py
dgl/view.py
dgl/_deprecate/__init__.py
dgl/_deprecate/frame.py
dgl/_deprecate/graph.py
dgl/_deprecate/kernel.py
dgl/_deprecate/nodeflow.py
dgl/_deprecate/udf.py
dgl/_deprecate/view.py
dgl/_deprecate/runtime/__init__.py
dgl/_deprecate/runtime/adapter.py
dgl/_deprecate/runtime/degree_bucketing.py
dgl/_deprecate/runtime/runtime.py
dgl/_deprecate/runtime/scheduler.py
dgl/_deprecate/runtime/spmv.py
dgl/_deprecate/runtime/ir/__init__.py
dgl/_deprecate/runtime/ir/executor.py
dgl/_deprecate/runtime/ir/program.py
dgl/_deprecate/runtime/ir/registry.py
dgl/_deprecate/runtime/ir/var.py
dgl/_ffi/__init__.py
dgl/_ffi/base.py
dgl/_ffi/function.py
dgl/_ffi/libinfo.py
dgl/_ffi/ndarray.py
dgl/_ffi/object.py
dgl/_ffi/object_generic.py
dgl/_ffi/runtime_ctypes.py
dgl/_ffi/_ctypes/__init__.py
dgl/_ffi/_ctypes/function.py
dgl/_ffi/_ctypes/ndarray.py
dgl/_ffi/_ctypes/object.py
dgl/_ffi/_ctypes/types.py
dgl/_ffi/_cy2/__init__.py
dgl/_ffi/_cy3/__init__.py
dgl/_ffi/_cy3/core.cpython-39-x86_64-linux-gnu.so
dgl/_ffi/_cython/core.cpp
dgl/backend/__init__.py
dgl/backend/backend.py
dgl/backend/set_default_backend.py
dgl/backend/mxnet/__init__.py
dgl/backend/mxnet/sparse.py
dgl/backend/mxnet/sparse_optim.py
dgl/backend/mxnet/tensor.py
dgl/backend/pytorch/__init__.py
dgl/backend/pytorch/sparse.py
dgl/backend/pytorch/tensor.py
dgl/backend/tensorflow/__init__.py
dgl/backend/tensorflow/sparse.py
dgl/backend/tensorflow/sparse_optim.py
dgl/backend/tensorflow/tensor.py
dgl/contrib/__init__.py
dgl/contrib/dis_kvstore.py
dgl/contrib/graph_store.py
dgl/contrib/data/__init__.py
dgl/contrib/data/knowledge_graph.py
dgl_cu110-0.6.1.dist-info/METADATA
dgl_cu110-0.6.1.dist-info/WHEEL
dgl_cu110-0.6.1.dist-info/top_level.txt
dgl_cu110-0.6.1.dist-info/RECORD
